pygame_geometry/__init__.py
pygame_geometry/abstract.py
pygame_geometry/abstractroom.py
pygame_geometry/activity.py
pygame_geometry/anatomies.py
pygame_geometry/angle.py
pygame_geometry/body.py
pygame_geometry/brick.py
pygame_geometry/builder.py
pygame_geometry/case.py
pygame_geometry/collider.py
pygame_geometry/colors.py
pygame_geometry/complexform.py
pygame_geometry/complexformv2.py
pygame_geometry/context.py
pygame_geometry/curves.py
pygame_geometry/diagram.py
pygame_geometry/dictmap.py
pygame_geometry/draw.py
pygame_geometry/economicmenu.py
pygame_geometry/entity.py
pygame_geometry/entitygroup.py
pygame_geometry/events.py
pygame_geometry/figure.py
pygame_geometry/force.py
pygame_geometry/game.py
pygame_geometry/graph.py
pygame_geometry/grapher.py
pygame_geometry/group.py
pygame_geometry/interpolation.py
pygame_geometry/logic.py
pygame_geometry/manager.py
pygame_geometry/map.py
pygame_geometry/material.py
pygame_geometry/materialcircle.py
pygame_geometry/materialform.py
pygame_geometry/materialformcollider.py
pygame_geometry/materialgroup.py
pygame_geometry/materialline.py
pygame_geometry/materialpoint.py
pygame_geometry/materialsegment.py
pygame_geometry/menu.py
pygame_geometry/motion.py
pygame_geometry/movinginterpolation.py
pygame_geometry/newmaterialform.py
pygame_geometry/painter.py
pygame_geometry/particles.py
pygame_geometry/pathfinder.py
pygame_geometry/perlin.py
pygame_geometry/physics.py
pygame_geometry/pixel.py
pygame_geometry/plane.py
pygame_geometry/polynomial.py
pygame_geometry/quadtree.py
pygame_geometry/rect.py
pygame_geometry/rectangle.py
pygame_geometry/set.py
pygame_geometry/sprite.py
pygame_geometry/spriteeditor.py
pygame_geometry/step.py
pygame_geometry/tools.py
pygame_geometry/tree.py
pygame_geometry/triangle.py
pygame_geometry/widgets.py
pygame_geometry/window.py
pygame_geometry/zone.py
pygame_geometry-0.1.2.dist-info/LICENSE
pygame_geometry-0.1.2.dist-info/METADATA
pygame_geometry-0.1.2.dist-info/WHEEL
pygame_geometry-0.1.2.dist-info/top_level.txt
pygame_geometry-0.1.2.dist-info/RECORD
