Metadata-Version: 2.1
Name: pygame-geometry
Version: 0.1.2
Summary: Geometry environment for pygame.
Home-page: https://github.com/MarcPartensky/Pygame-Geometry
Author: Mazex
Author-email: marc.partensky@gmail.com
License: UNKNOWN
Platform: UNKNOWN
Classifier: Programming Language :: Python :: 3
Classifier: License :: OSI Approved :: MIT License
Classifier: Operating System :: OS Independent
Requires-Python: >=3.7
